django_payments-3.1.0.dist-info/licenses/LICENSE
payments/__init__.py
payments/core.py
payments/fields.py
payments/forms.py
payments/models.py
payments/signals.py
payments/test_core.py
payments/urls.py
payments/utils.py
payments/version.py
payments/widgets.py
payments/authorizenet/__init__.py
payments/authorizenet/forms.py
payments/authorizenet/test_authorizenet.py
payments/braintree/__init__.py
payments/braintree/forms.py
payments/braintree/test_braintree.py
payments/coinbase/__init__.py
payments/coinbase/test_coinbase.py
payments/cybersource/__init__.py
payments/cybersource/forms.py
payments/cybersource/test_cybersource.py
payments/cybersource/xml/CyberSourceTransaction_1.101.test.wsdl
payments/cybersource/xml/CyberSourceTransaction_1.101.wsdl
payments/cybersource/xml/CyberSourceTransaction_1.101.xsd
payments/dotpay/__init__.py
payments/dotpay/forms.py
payments/dotpay/test_dotpay.py
payments/dummy/__init__.py
payments/dummy/forms.py
payments/dummy/test_dummy.py
payments/locale/de/LC_MESSAGES/django.mo
payments/locale/de/LC_MESSAGES/django.po
payments/locale/en/LC_MESSAGES/django.mo
payments/locale/en/LC_MESSAGES/django.po
payments/locale/es/LC_MESSAGES/django.mo
payments/locale/es/LC_MESSAGES/django.po
payments/locale/fr/LC_MESSAGES/django.mo
payments/locale/fr/LC_MESSAGES/django.po
payments/locale/it/LC_MESSAGES/django.mo
payments/locale/it/LC_MESSAGES/django.po
payments/locale/ja/LC_MESSAGES/django.mo
payments/locale/ja/LC_MESSAGES/django.po
payments/locale/ko/LC_MESSAGES/django.mo
payments/locale/ko/LC_MESSAGES/django.po
payments/locale/pl/LC_MESSAGES/django.mo
payments/locale/pl/LC_MESSAGES/django.po
payments/locale/pt_BR/LC_MESSAGES/django.mo
payments/locale/pt_BR/LC_MESSAGES/django.po
payments/locale/ru/LC_MESSAGES/django.mo
payments/locale/ru/LC_MESSAGES/django.po
payments/locale/sk/LC_MESSAGES/django.mo
payments/locale/sk/LC_MESSAGES/django.po
payments/locale/tr/LC_MESSAGES/django.mo
payments/locale/tr/LC_MESSAGES/django.po
payments/locale/uk/LC_MESSAGES/django.mo
django_payments-3.1.0.dist-info/METADATA
django_payments-3.1.0.dist-info/WHEEL
django_payments-3.1.0.dist-info/top_level.txt
django_payments-3.1.0.dist-info/RECORD
