Metadata-Version: 2.4
Name: django-payments
Version: 3.1.0
Summary: Universal payment handling for Django
Author-email: Mirumee Software <hello@mirumee.com>
License: BSD
Project-URL: homepage, https://github.com/jazzband/django-payments
Project-URL: documentation, https://django-payments.readthedocs.io/
Project-URL: changelog, https://django-payments.readthedocs.io/en/latest/changelog.html
Project-URL: issues, https://github.com/jazzband/django-payments/issues
Keywords: payments
Classifier: Environment :: Web Environment
Classifier: Framework :: Django :: 4.2
Classifier: Framework :: Django :: 5.0
Classifier: Framework :: Django :: 5.1
Classifier: Framework :: Django :: 5.2
Classifier: Intended Audience :: Developers
Classifier: License :: OSI Approved :: BSD License
Classifier: Operating System :: OS Independent
Classifier: Programming Language :: Python
Classifier: Programming Language :: Python :: 3.9
Classifier: Programming Language :: Python :: 3.10
Classifier: Programming Language :: Python :: 3.11
Classifier: Programming Language :: Python :: 3.12
Classifier: Programming Language :: Python :: 3.13
Classifier: Framework :: Django
Classifier: Topic :: Software Development :: Libraries :: Application Frameworks
Classifier: Topic :: Software Development :: Libraries :: Python Modules
Requires-Python: >=3.9
License-File: LICENSE
Requires-Dist: Django<5.3,>=4.2
Requires-Dist: requests>=1.2.0
Requires-Dist: django-phonenumber-field[phonenumberslite]>=5.0.0
Provides-Extra: braintree
Requires-Dist: braintree>=3.14.0; extra == "braintree"
Provides-Extra: cybersource
Requires-Dist: suds-community>=0.6; extra == "cybersource"
Provides-Extra: dev
Requires-Dist: coverage; extra == "dev"
Requires-Dist: django-stubs[compatible-mypy]; extra == "dev"
Requires-Dist: mock; extra == "dev"
Requires-Dist: pytest; extra == "dev"
Requires-Dist: pytest-cov; extra == "dev"
Requires-Dist: pytest-django; extra == "dev"
Requires-Dist: types-braintree; extra == "dev"
Requires-Dist: types-dj-database-url; extra == "dev"
Requires-Dist: types-requests; extra == "dev"
Requires-Dist: types-stripe; extra == "dev"
Requires-Dist: types-xmltodict; extra == "dev"
Provides-Extra: docs
Requires-Dist: sphinx_rtd_theme; extra == "docs"
Provides-Extra: mercadopago
Requires-Dist: mercadopago<3.0.0,>=2.0.0; extra == "mercadopago"
Provides-Extra: sagepay
Requires-Dist: cryptography>=1.1.0; extra == "sagepay"
Provides-Extra: sofort
Requires-Dist: xmltodict>=0.9.2; extra == "sofort"
Provides-Extra: stripe
Requires-Dist: stripe>=2.6.0; extra == "stripe"
Dynamic: license-file
